mongo_id_marshaller/__init__.py
mongo_id_marshaller/mongo_id.py
mongo_id_marshaller-1.0.0.dist-info/METADATA
mongo_id_marshaller-1.0.0.dist-info/WHEEL
mongo_id_marshaller-1.0.0.dist-info/top_level.txt
mongo_id_marshaller-1.0.0.dist-info/RECORD
