Metadata-Version: 2.1
Name: mongo-id-marshaller
Version: 1.0.0
Summary: A small library that marshals Mongo ObjectIds
Home-page: https://github.com/joegasewicz/mongo-id-marshaller
Author: Joe Gasewicz
Author-email: joegasewicz@gmail.com
License: UNKNOWN
Platform: UNKNOWN
Classifier: Programming Language :: Python :: 3
Classifier: Programming Language :: Python :: 3.7
Classifier: Programming Language :: Python :: 3.8
Classifier: Operating System :: OS Independent
Provides-Extra: dev
Requires-Dist: pytest ; extra == 'dev'
Requires-Dist: bson ; extra == 'dev'
Requires-Dist: mongomock ; extra == 'dev'
